<SheetProperties>
  <SheetFont>
    <FontName>Tahoma</FontName>
    <PointSize1000>8000</PointSize1000>
  </SheetFont>
  <Name>Outros</Name>
  <BkgColor>
    <PrimaryCol>
      <Col>
        <Red>248</Red>
        <Green>248</Green>
        <Blue>248</Blue>
      </Col>
    </PrimaryCol>
  </BkgColor>
  <BkgImageSettings>
    <ImageStyle>
      <StretchMode>IMAGE_NOSTRETCH</StretchMode>
    </ImageStyle>
  </BkgImageSettings>
  <UserPermissions>
    <AddSheetObject>true</AddSheetObject>
    <RemoveSheetObject>true</RemoveSheetObject>
    <MoveSizeSheetObject>true</MoveSizeSheetObject>
    <CopyCloneSheetObject>true</CopyCloneSheetObject>
    <RemoveSheet>true</RemoveSheet>
    <AccessSheetObjectProperties>true</AccessSheetObjectProperties>
    <AccessSheetProperties>true</AccessSheetProperties>
  </UserPermissions>
  <SheetId>SH11</SheetId>
  <TabAttr>
    <BgColor>
      <PrimaryCol>
        <Col>
          <Red>248</Red>
          <Green>248</Green>
          <Blue>248</Blue>
        </Col>
      </PrimaryCol>
    </BgColor>
    <Mode>1</Mode>
  </TabAttr>
  <ChildObjects>
    <FrameParentDef>
      <ObjectId>TX41</ObjectId>
      <Rect>
        <Left>44</Left>
        <Top>213</Top>
        <Width>488</Width>
        <Height>100</Height>
      </Rect>
      <MinimizedRect>
        <Width>297</Width>
        <Height>102</Height>
      </MinimizedRect>
      <ShowMode>1</ShowMode>
      <ZedLevel>-1</ZedLevel>
    </FrameParentDef>
    <FrameParentDef>
      <ObjectId>LB61</ObjectId>
      <Rect>
        <Left>38</Left>
        <Top>731</Top>
        <Width>244</Width>
        <Height>119</Height>
      </Rect>
      <MinimizedRect>
        <Width>297</Width>
        <Height>102</Height>
      </MinimizedRect>
      <ShowMode>1</ShowMode>
    </FrameParentDef>
    <FrameParentDef>
      <ObjectId>SO07</ObjectId>
      <Rect>
        <Left>13</Left>
        <Top>47</Top>
        <Width>609</Width>
        <Height>100</Height>
      </Rect>
      <MinimizedRect>
        <Width>297</Width>
        <Height>102</Height>
      </MinimizedRect>
      <ShowMode>1</ShowMode>
    </FrameParentDef>
    <FrameParentDef>
      <ObjectId>LB60</ObjectId>
      <Rect>
        <Left>38</Left>
        <Top>884</Top>
        <Width>244</Width>
        <Height>303</Height>
      </Rect>
      <MinimizedRect>
        <Width>297</Width>
        <Height>102</Height>
      </MinimizedRect>
      <ShowMode>1</ShowMode>
    </FrameParentDef>
    <FrameParentDef>
      <ObjectId>LB62</ObjectId>
      <Rect>
        <Left>44</Left>
        <Top>356</Top>
        <Width>494</Width>
        <Height>344</Height>
      </Rect>
      <MinimizedRect>
        <Width>297</Width>
        <Height>102</Height>
      </MinimizedRect>
      <ShowMode>1</ShowMode>
    </FrameParentDef>
    <FrameParentDef>
      <ObjectId>CT03</ObjectId>
      <Rect>
        <Left>638</Left>
        <Top>53</Top>
        <Width>3106</Width>
        <Height>1697</Height>
      </Rect>
      <MinimizedRect>
        <Width>297</Width>
        <Height>102</Height>
      </MinimizedRect>
      <ShowMode>1</ShowMode>
    </FrameParentDef>
    <FrameParentDef>
      <ObjectId>LB71</ObjectId>
      <Rect>
        <Left>322</Left>
        <Top>1197</Top>
        <Width>250</Width>
        <Height>238</Height>
      </Rect>
      <MinimizedRect>
        <Width>297</Width>
        <Height>102</Height>
      </MinimizedRect>
      <ShowMode>1</ShowMode>
    </FrameParentDef>
    <FrameParentDef>
      <ObjectId>LB72</ObjectId>
      <Rect>
        <Left>25</Left>
        <Top>1197</Top>
        <Width>250</Width>
        <Height>203</Height>
      </Rect>
      <MinimizedRect>
        <Width>297</Width>
        <Height>102</Height>
      </MinimizedRect>
      <ShowMode>1</ShowMode>
    </FrameParentDef>
  </ChildObjects>
</SheetProperties>
