<SheetProperties>
  <SheetFont>
    <FontName>Tahoma</FontName>
    <PointSize1000>8000</PointSize1000>
  </SheetFont>
  <Name>Pivot</Name>
  <BkgColor>
    <PrimaryCol>
      <Col>
        <Red>248</Red>
        <Green>248</Green>
        <Blue>248</Blue>
      </Col>
    </PrimaryCol>
  </BkgColor>
  <BkgImageSettings>
    <ImageStyle>
      <StretchMode>IMAGE_NOSTRETCH</StretchMode>
    </ImageStyle>
  </BkgImageSettings>
  <UserPermissions>
    <AddSheetObject>true</AddSheetObject>
    <RemoveSheetObject>true</RemoveSheetObject>
    <MoveSizeSheetObject>true</MoveSizeSheetObject>
    <CopyCloneSheetObject>true</CopyCloneSheetObject>
    <RemoveSheet>true</RemoveSheet>
    <AccessSheetObjectProperties>true</AccessSheetObjectProperties>
    <AccessSheetProperties>true</AccessSheetProperties>
  </UserPermissions>
  <SheetId>SH05</SheetId>
  <TabAttr>
    <BgColor>
      <PrimaryCol>
        <Col>
          <Red>248</Red>
          <Green>248</Green>
          <Blue>248</Blue>
        </Col>
      </PrimaryCol>
    </BgColor>
    <Mode>1</Mode>
  </TabAttr>
  <ChildObjects>
    <FrameParentDef>
      <ObjectId>TX24</ObjectId>
      <Rect>
        <Left>1644</Left>
        <Top>44</Top>
        <Width>397</Width>
        <Height>219</Height>
      </Rect>
      <MinimizedRect>
        <Width>297</Width>
        <Height>102</Height>
      </MinimizedRect>
      <ShowMode>1</ShowMode>
      <ZedLevel>-1</ZedLevel>
    </FrameParentDef>
    <FrameParentDef>
      <ObjectId>TX26</ObjectId>
      <Rect>
        <Left>1181</Left>
        <Top>44</Top>
        <Width>397</Width>
        <Height>219</Height>
      </Rect>
      <MinimizedRect>
        <Width>297</Width>
        <Height>102</Height>
      </MinimizedRect>
      <ShowMode>1</ShowMode>
      <ZedLevel>-1</ZedLevel>
    </FrameParentDef>
    <FrameParentDef>
      <ObjectId>TX25</ObjectId>
      <Rect>
        <Left>719</Left>
        <Top>44</Top>
        <Width>397</Width>
        <Height>219</Height>
      </Rect>
      <MinimizedRect>
        <Width>297</Width>
        <Height>102</Height>
      </MinimizedRect>
      <ShowMode>1</ShowMode>
      <ZedLevel>-1</ZedLevel>
    </FrameParentDef>
    <FrameParentDef>
      <ObjectId>TX27</ObjectId>
      <Rect>
        <Left>2106</Left>
        <Top>44</Top>
        <Width>466</Width>
        <Height>219</Height>
      </Rect>
      <MinimizedRect>
        <Width>297</Width>
        <Height>102</Height>
      </MinimizedRect>
      <ShowMode>1</ShowMode>
      <ZedLevel>-1</ZedLevel>
    </FrameParentDef>
    <FrameParentDef>
      <ObjectId>LB39</ObjectId>
      <Rect>
        <Left>372</Left>
        <Top>544</Top>
        <Width>263</Width>
        <Height>725</Height>
      </Rect>
      <MinimizedRect>
        <Width>297</Width>
        <Height>102</Height>
      </MinimizedRect>
      <ShowMode>1</ShowMode>
    </FrameParentDef>
    <FrameParentDef>
      <ObjectId>CH17</ObjectId>
      <Rect>
        <Left>719</Left>
        <Top>338</Top>
        <Width>3541</Width>
        <Height>1569</Height>
      </Rect>
      <MinimizedRect>
        <Left>753</Left>
        <Top>353</Top>
        <Width>428</Width>
        <Height>103</Height>
      </MinimizedRect>
      <ShowMode>1</ShowMode>
    </FrameParentDef>
    <FrameParentDef>
      <ObjectId>LB45</ObjectId>
      <Rect>
        <Left>44</Left>
        <Top>1300</Top>
        <Width>250</Width>
        <Height>463</Height>
      </Rect>
      <MinimizedRect>
        <Width>297</Width>
        <Height>102</Height>
      </MinimizedRect>
      <ShowMode>1</ShowMode>
    </FrameParentDef>
    <FrameParentDef>
      <ObjectId>LB38</ObjectId>
      <Rect>
        <Left>34</Left>
        <Top>216</Top>
        <Width>300</Width>
        <Height>213</Height>
      </Rect>
      <MinimizedRect>
        <Width>297</Width>
        <Height>102</Height>
      </MinimizedRect>
      <ShowMode>1</ShowMode>
    </FrameParentDef>
    <FrameParentDef>
      <ObjectId>SO02</ObjectId>
      <Rect>
        <Left>63</Left>
        <Top>44</Top>
        <Width>547</Width>
        <Height>100</Height>
      </Rect>
      <MinimizedRect>
        <Width>297</Width>
        <Height>102</Height>
      </MinimizedRect>
      <ShowMode>1</ShowMode>
    </FrameParentDef>
    <FrameParentDef>
      <ObjectId>LB41</ObjectId>
      <Rect>
        <Left>34</Left>
        <Top>941</Top>
        <Width>294</Width>
        <Height>344</Height>
      </Rect>
      <MinimizedRect>
        <Width>297</Width>
        <Height>102</Height>
      </MinimizedRect>
      <ShowMode>1</ShowMode>
    </FrameParentDef>
    <FrameParentDef>
      <ObjectId>LB43</ObjectId>
      <Rect>
        <Left>34</Left>
        <Top>413</Top>
        <Width>297</Width>
        <Height>484</Height>
      </Rect>
      <MinimizedRect>
        <Width>297</Width>
        <Height>102</Height>
      </MinimizedRect>
      <ShowMode>1</ShowMode>
    </FrameParentDef>
    <FrameParentDef>
      <ObjectId>LB42</ObjectId>
      <Rect>
        <Left>375</Left>
        <Top>216</Top>
        <Width>266</Width>
        <Height>250</Height>
      </Rect>
      <MinimizedRect>
        <Width>297</Width>
        <Height>102</Height>
      </MinimizedRect>
      <ShowMode>1</ShowMode>
    </FrameParentDef>
  </ChildObjects>
</SheetProperties>
