<SheetProperties>
  <SheetFont>
    <FontName>Tahoma</FontName>
    <PointSize1000>8000</PointSize1000>
  </SheetFont>
  <Name>DPD por Comprador/Loja</Name>
  <BkgColor>
    <PrimaryCol>
      <Col>
        <Red>248</Red>
        <Green>248</Green>
        <Blue>248</Blue>
      </Col>
    </PrimaryCol>
  </BkgColor>
  <BkgImageSettings>
    <ImageStyle>
      <StretchMode>IMAGE_NOSTRETCH</StretchMode>
    </ImageStyle>
  </BkgImageSettings>
  <UserPermissions>
    <AddSheetObject>true</AddSheetObject>
    <RemoveSheetObject>true</RemoveSheetObject>
    <MoveSizeSheetObject>true</MoveSizeSheetObject>
    <CopyCloneSheetObject>true</CopyCloneSheetObject>
    <RemoveSheet>true</RemoveSheet>
    <AccessSheetObjectProperties>true</AccessSheetObjectProperties>
    <AccessSheetProperties>true</AccessSheetProperties>
  </UserPermissions>
  <SheetId>SH14</SheetId>
  <TabAttr>
    <BgColor>
      <PrimaryCol>
        <Col>
          <Red>248</Red>
          <Green>248</Green>
          <Blue>248</Blue>
        </Col>
      </PrimaryCol>
    </BgColor>
    <Mode>1</Mode>
  </TabAttr>
  <ChildObjects>
    <FrameParentDef>
      <ObjectId>TX47</ObjectId>
      <Rect>
        <Left>672</Left>
        <Top>34</Top>
        <Width>600</Width>
        <Height>194</Height>
      </Rect>
      <MinimizedRect>
        <Width>297</Width>
        <Height>102</Height>
      </MinimizedRect>
      <ShowMode>1</ShowMode>
      <ZedLevel>-1</ZedLevel>
    </FrameParentDef>
    <FrameParentDef>
      <ObjectId>SO39</ObjectId>
      <Rect>
        <Left>38</Left>
        <Top>47</Top>
        <Width>503</Width>
        <Height>100</Height>
      </Rect>
      <MinimizedRect>
        <Width>297</Width>
        <Height>102</Height>
      </MinimizedRect>
      <ShowMode>1</ShowMode>
    </FrameParentDef>
    <FrameParentDef>
      <ObjectId>MB94</ObjectId>
      <Rect>
        <Left>41</Left>
        <Top>1925</Top>
        <Width>725</Width>
        <Height>363</Height>
      </Rect>
      <MinimizedRect>
        <Width>297</Width>
        <Height>102</Height>
      </MinimizedRect>
      <ShowMode>1</ShowMode>
    </FrameParentDef>
    <FrameParentDef>
      <ObjectId>MB95</ObjectId>
      <Rect>
        <Left>41</Left>
        <Top>1478</Top>
        <Width>553</Width>
        <Height>206</Height>
      </Rect>
      <MinimizedRect>
        <Width>297</Width>
        <Height>102</Height>
      </MinimizedRect>
      <ShowMode>1</ShowMode>
    </FrameParentDef>
    <FrameParentDef>
      <ObjectId>LB167</ObjectId>
      <Rect>
        <Left>266</Left>
        <Top>1709</Top>
        <Width>269</Width>
        <Height>316</Height>
      </Rect>
      <MinimizedRect>
        <Width>297</Width>
        <Height>102</Height>
      </MinimizedRect>
      <ShowMode>1</ShowMode>
    </FrameParentDef>
    <FrameParentDef>
      <ObjectId>LB168</ObjectId>
      <Rect>
        <Left>41</Left>
        <Top>1706</Top>
        <Width>209</Width>
        <Height>234</Height>
      </Rect>
      <MinimizedRect>
        <Width>297</Width>
        <Height>102</Height>
      </MinimizedRect>
      <ShowMode>1</ShowMode>
    </FrameParentDef>
    <FrameParentDef>
      <ObjectId>LB166</ObjectId>
      <Rect>
        <Left>44</Left>
        <Top>175</Top>
        <Width>494</Width>
        <Height>644</Height>
      </Rect>
      <MinimizedRect>
        <Width>297</Width>
        <Height>102</Height>
      </MinimizedRect>
      <ShowMode>1</ShowMode>
    </FrameParentDef>
    <FrameParentDef>
      <ObjectId>LB165</ObjectId>
      <Rect>
        <Left>44</Left>
        <Top>813</Top>
        <Width>497</Width>
        <Height>472</Height>
      </Rect>
      <MinimizedRect>
        <Width>297</Width>
        <Height>102</Height>
      </MinimizedRect>
      <ShowMode>1</ShowMode>
    </FrameParentDef>
    <FrameParentDef>
      <ObjectId>MB93</ObjectId>
      <Rect>
        <Left>44</Left>
        <Top>1263</Top>
        <Width>509</Width>
        <Height>231</Height>
      </Rect>
      <MinimizedRect>
        <Width>297</Width>
        <Height>102</Height>
      </MinimizedRect>
      <ShowMode>1</ShowMode>
    </FrameParentDef>
    <FrameParentDef>
      <ObjectId>CH76</ObjectId>
      <Rect>
        <Left>3347</Left>
        <Top>259</Top>
        <Width>1566</Width>
        <Height>2188</Height>
      </Rect>
      <MinimizedRect>
        <Width>297</Width>
        <Height>102</Height>
      </MinimizedRect>
      <ShowMode>1</ShowMode>
    </FrameParentDef>
    <FrameParentDef>
      <ObjectId>CH75</ObjectId>
      <Rect>
        <Left>2031</Left>
        <Top>256</Top>
        <Width>1566</Width>
        <Height>2188</Height>
      </Rect>
      <MinimizedRect>
        <Width>297</Width>
        <Height>102</Height>
      </MinimizedRect>
      <ShowMode>1</ShowMode>
    </FrameParentDef>
    <FrameParentDef>
      <ObjectId>CH74</ObjectId>
      <Rect>
        <Left>675</Left>
        <Top>259</Top>
        <Width>1566</Width>
        <Height>2188</Height>
      </Rect>
      <MinimizedRect>
        <Width>297</Width>
        <Height>102</Height>
      </MinimizedRect>
      <ShowMode>1</ShowMode>
    </FrameParentDef>
  </ChildObjects>
</SheetProperties>
