<DocInternals>
  <AlwaysLoose>
    <bool>false</bool>
    <bool>false</bool>
    <bool>false</bool>
    <bool>false</bool>
    <bool>false</bool>
    <bool>false</bool>
    <bool>false</bool>
    <bool>false</bool>
    <bool>false</bool>
    <bool>false</bool>
    <bool>false</bool>
  </AlwaysLoose>
  <FieldSrcTables>
    <String>6</String>
    <String>4</String>
    <String>CAD_LOJA</String>
    <String>CAD_RESTAURANTE</String>
    <String>VENDA_CUPOM_CAPA</String>
    <String>VENDA_CUPOM_PRODUTO</String>
    <String>7</String>
    <String>1</String>
    <String>CAD_LOJA</String>
    <String>8</String>
    <String>1</String>
    <String>CAD_LOJA</String>
    <String>9</String>
    <String>1</String>
    <String>CAD_LOJA</String>
    <String>10</String>
    <String>3</String>
    <String>CAD_RESTAURANTE</String>
    <String>VENDA_CUPOM_CAPA</String>
    <String>VENDA_CUPOM_PRODUTO</String>
    <String>11</String>
    <String>1</String>
    <String>CAD_RESTAURANTE</String>
    <String>12</String>
    <String>1</String>
    <String>CAD_RESTAURANTE</String>
    <String>13</String>
    <String>2</String>
    <String>GRUPO_COMPRADOR</String>
    <String>DEPARTAMENTOS</String>
    <String>14</String>
    <String>1</String>
    <String>GRUPO_COMPRADOR</String>
    <String>15</String>
    <String>1</String>
    <String>DEPARTAMENTOS</String>
    <String>16</String>
    <String>1</String>
    <String>DEPARTAMENTOS</String>
    <String>17</String>
    <String>1</String>
    <String>DEPARTAMENTOS</String>
    <String>18</String>
    <String>1</String>
    <String>DEPARTAMENTOS</String>
    <String>19</String>
    <String>3</String>
    <String>DEPARTAMENTOS</String>
    <String>FLG_METADADOS</String>
    <String>VENDA_CUPOM_PRODUTO</String>
    <String>20</String>
    <String>1</String>
    <String>DEPARTAMENTOS</String>
    <String>21</String>
    <String>1</String>
    <String>DEPARTAMENTOS</String>
    <String>22</String>
    <String>1</String>
    <String>DEPARTAMENTOS</String>
    <String>23</String>
    <String>1</String>
    <String>DEPARTAMENTOS</String>
    <String>24</String>
    <String>1</String>
    <String>FLG_METADADOS</String>
    <String>25</String>
    <String>1</String>
    <String>FLG_METADADOS</String>
    <String>26</String>
    <String>1</String>
    <String>FLG_METADADOS</String>
    <String>27</String>
    <String>1</String>
    <String>FLG_METADADOS</String>
    <String>28</String>
    <String>1</String>
    <String>FLG_METADADOS</String>
    <String>29</String>
    <String>1</String>
    <String>FLG_METADADOS</String>
    <String>30</String>
    <String>1</String>
    <String>FLG_METADADOS</String>
    <String>31</String>
    <String>2</String>
    <String>VENDA_CUPOM_CAPA</String>
    <String>VENDA_CUPOM_PRODUTO</String>
    <String>32</String>
    <String>2</String>
    <String>VENDA_CUPOM_CAPA</String>
    <String>VENDA_CUPOM_PRODUTO</String>
    <String>33</String>
    <String>2</String>
    <String>VENDA_CUPOM_CAPA</String>
    <String>VENDA_CUPOM_PRODUTO</String>
    <String>34</String>
    <String>2</String>
    <String>VENDA_CUPOM_CAPA</String>
    <String>VENDA_CUPOM_PRODUTO</String>
    <String>35</String>
    <String>2</String>
    <String>VENDA_CUPOM_CAPA</String>
    <String>VENDA_CUPOM_PRODUTO</String>
    <String>36</String>
    <String>2</String>
    <String>VENDA_CUPOM_CAPA</String>
    <String>VENDA_CUPOM_PRODUTO</String>
    <String>37</String>
    <String>2</String>
    <String>VENDA_CUPOM_CAPA</String>
    <String>VENDA_CUPOM_PRODUTO</String>
    <String>38</String>
    <String>1</String>
    <String>VENDA_CUPOM_CAPA</String>
    <String>39</String>
    <String>1</String>
    <String>VENDA_CUPOM_CAPA</String>
    <String>40</String>
    <String>1</String>
    <String>VENDA_CUPOM_CAPA</String>
    <String>41</String>
    <String>1</String>
    <String>VENDA_CUPOM_CAPA</String>
    <String>42</String>
    <String>1</String>
    <String>VENDA_CUPOM_CAPA</String>
    <String>43</String>
    <String>1</String>
    <String>VENDA_CUPOM_CAPA</String>
    <String>44</String>
    <String>1</String>
    <String>VENDA_CUPOM_PRODUTO</String>
    <String>45</String>
    <String>1</String>
    <String>VENDA_CUPOM_PRODUTO</String>
    <String>46</String>
    <String>1</String>
    <String>VENDA_CUPOM_PRODUTO</String>
    <String>47</String>
    <String>1</String>
    <String>VENDA_CUPOM_PRODUTO</String>
    <String>48</String>
    <String>1</String>
    <String>VENDA_CUPOM_PRODUTO</String>
  </FieldSrcTables>
  <TableViewData>
    <CtlInfo>
      <InternalView>
        <Tables>
          <TableViewTableWinSaveInfo>
            <Pos>
              <Left>1130</Left>
              <Top>623</Top>
              <Width>100</Width>
              <Height>78</Height>
            </Pos>
            <Caption>CAD_LOJA</Caption>
          </TableViewTableWinSaveInfo>
          <TableViewTableWinSaveInfo>
            <Pos>
              <Left>223</Left>
              <Top>113</Top>
              <Width>100</Width>
              <Height>61</Height>
            </Pos>
            <Caption>GRUPO_COMPRADOR</Caption>
          </TableViewTableWinSaveInfo>
          <TableViewTableWinSaveInfo>
            <Pos>
              <Left>382</Left>
              <Top>97</Top>
              <Width>100</Width>
              <Height>163</Height>
            </Pos>
            <Caption>DEPARTAMENTOS</Caption>
          </TableViewTableWinSaveInfo>
          <TableViewTableWinSaveInfo>
            <Pos>
              <Left>706</Left>
              <Top>435</Top>
              <Width>100</Width>
              <Height>129</Height>
            </Pos>
            <Caption>FLG_METADADOS</Caption>
          </TableViewTableWinSaveInfo>
          <TableViewTableWinSaveInfo>
            <Pos>
              <Left>103</Left>
              <Top>86</Top>
              <Width>100</Width>
              <Height>197</Height>
            </Pos>
            <Caption>VENDA_CUPOM_CAPA</Caption>
          </TableViewTableWinSaveInfo>
          <TableViewTableWinSaveInfo>
            <Pos>
              <Left>365</Left>
              <Top>449</Top>
              <Width>137</Width>
              <Height>248</Height>
            </Pos>
            <Caption>VENDA_CUPOM_PRODUTO</Caption>
          </TableViewTableWinSaveInfo>
          <TableViewTableWinSaveInfo>
            <Pos>
              <Left>812</Left>
              <Top>326</Top>
              <Width>100</Width>
              <Height>146</Height>
            </Pos>
            <Caption>$Syn 1 Table</Caption>
          </TableViewTableWinSaveInfo>
          <TableViewTableWinSaveInfo>
            <Pos>
              <Left>571</Left>
              <Top>43</Top>
              <Width>100</Width>
              <Height>95</Height>
            </Pos>
            <Caption>CAD_RESTAURANTE</Caption>
          </TableViewTableWinSaveInfo>
          <TableViewTableWinSaveInfo>
            <Pos>
              <Left>625</Left>
              <Top>257</Top>
              <Width>100</Width>
              <Height>248</Height>
            </Pos>
            <Caption>$Syn 3 Table</Caption>
          </TableViewTableWinSaveInfo>
        </Tables>
      </InternalView>
    </CtlInfo>
  </TableViewData>
  <SavedByVersion>10.00.8811.0409</SavedByVersion>
  <PersonalEditionHash>18BAAC69ABBE879BC41A06F4FE33E440D8F3901C8B91525956E6854CB143E440266B005C118EC1FED611864CB143E440266B005C118EC1FE5C5EA337CDFC0A99</PersonalEditionHash>
  <FieldTags>
    <ScriptBased>
      <FieldTagData>
        <Tag>$key</Tag>
        <FieldNames>
          <String>$Field</String>
          <String>$Table</String>
          <String>COD_LOJA</String>
          <String>COD_USUARIO</String>
          <String>COD_PRODUTO</String>
          <String>$Syn 1</String>
          <String>$Syn 3</String>
        </FieldNames>
      </FieldTagData>
      <FieldTagData>
        <Tag>$hidden</Tag>
        <FieldNames>
          <String>$Field</String>
          <String>$Table</String>
          <String>$Rows</String>
          <String>$Fields</String>
          <String>$FieldNo</String>
          <String>$Info</String>
          <String>$Syn 1</String>
          <String>$Syn 2</String>
          <String>$Syn 3</String>
        </FieldNames>
      </FieldTagData>
      <FieldTagData>
        <Tag>$system</Tag>
        <FieldNames>
          <String>$Field</String>
          <String>$Table</String>
          <String>$Rows</String>
          <String>$Fields</String>
          <String>$FieldNo</String>
          <String>$Info</String>
        </FieldNames>
      </FieldTagData>
      <FieldTagData>
        <Tag>$ascii</Tag>
        <FieldNames>
          <String>$Field</String>
          <String>$Table</String>
          <String>$Info</String>
          <String>NO_LOJA</String>
          <String>NO_REGIONAL</String>
          <String>TIPO_RESTAURANTE</String>
          <String>NO_COMPRADOR</String>
          <String>NO_DEPARTAMENTO</String>
          <String>NO_SECAO</String>
          <String>MTD_ORG_PROD</String>
          <String>NO_MES_454</String>
          <String>HORA</String>
        </FieldNames>
      </FieldTagData>
      <FieldTagData>
        <Tag>$text</Tag>
        <FieldNames>
          <String>$Field</String>
          <String>$Table</String>
          <String>$Info</String>
          <String>NO_LOJA</String>
          <String>NO_REGIONAL</String>
          <String>NO_RESTAURANTE</String>
          <String>TIPO_RESTAURANTE</String>
          <String>NO_COMPRADOR</String>
          <String>NO_DEPARTAMENTO</String>
          <String>NO_SECAO</String>
          <String>NO_GRUPO</String>
          <String>NO_SUBGRUPO</String>
          <String>DES_FANTASIA</String>
          <String>MTD_ORG_PROD</String>
          <String>NO_MES_454</String>
          <String>HORA</String>
          <String>DES_PRODUTO_CHEFF</String>
        </FieldNames>
      </FieldTagData>
      <FieldTagData>
        <Tag>$numeric</Tag>
        <FieldNames>
          <String>$Rows</String>
          <String>$Fields</String>
          <String>$FieldNo</String>
          <String>COD_LOJA</String>
          <String>DTA_ABERTURA</String>
          <String>COD_RESTAURANTE</String>
          <String>COD_USUARIO</String>
          <String>COD_PRODUTO</String>
          <String>COD_FORNECEDOR</String>
          <String>COD_EAN</String>
          <String>MTD_MP</String>
          <String>MTD_IMP_PROP</String>
          <String>MTD_IMP</String>
          <String>MTD_NOTAVEL</String>
          <String>MTD_ULTRA_NOTAVEL</String>
          <String>DATA</String>
          <String>ANO_454</String>
          <String>MES_454</String>
          <String>SEMANA_454</String>
          <String>CAIXA</String>
          <String>CUPOM</String>
          <String>CPF</String>
          <String>VLR_PRODUTOS_CUPOM</String>
          <String>VLR_SERVICO</String>
          <String>VLR_TOTAL_CUPOM</String>
          <String>QTDE_PESSOAS</String>
          <String>VLR_UNITARIO_PROD</String>
          <String>QUANTIDADE</String>
          <String>VLR_DSCONTO_PROD</String>
          <String>VLR_TOTAL_PRODUTO</String>
        </FieldNames>
      </FieldTagData>
      <FieldTagData>
        <Tag>$integer</Tag>
        <FieldNames>
          <String>$Rows</String>
          <String>$Fields</String>
          <String>$FieldNo</String>
          <String>COD_LOJA</String>
          <String>DTA_ABERTURA</String>
          <String>COD_RESTAURANTE</String>
          <String>COD_USUARIO</String>
          <String>COD_PRODUTO</String>
          <String>COD_FORNECEDOR</String>
          <String>COD_EAN</String>
          <String>MTD_MP</String>
          <String>MTD_IMP_PROP</String>
          <String>MTD_IMP</String>
          <String>MTD_NOTAVEL</String>
          <String>MTD_ULTRA_NOTAVEL</String>
          <String>DATA</String>
          <String>ANO_454</String>
          <String>MES_454</String>
          <String>SEMANA_454</String>
          <String>CAIXA</String>
          <String>CUPOM</String>
          <String>CPF</String>
          <String>QTDE_PESSOAS</String>
        </FieldNames>
      </FieldTagData>
      <FieldTagData>
        <Tag>$timestamp</Tag>
        <FieldNames>
          <String>DTA_ABERTURA</String>
          <String>DATA</String>
        </FieldNames>
      </FieldTagData>
      <FieldTagData>
        <Tag>$date</Tag>
        <FieldNames>
          <String>DTA_ABERTURA</String>
          <String>DATA</String>
        </FieldNames>
      </FieldTagData>
      <FieldTagData>
        <Tag>$keypart</Tag>
        <FieldNames>
          <String>COD_RESTAURANTE</String>
          <String>DATA</String>
          <String>ANO_454</String>
          <String>MES_454</String>
          <String>NO_MES_454</String>
          <String>SEMANA_454</String>
          <String>CAIXA</String>
          <String>CUPOM</String>
          <String>$Syn 2</String>
        </FieldNames>
      </FieldTagData>
      <FieldTagData>
        <Tag>$synthetic</Tag>
        <FieldNames>
          <String>$Syn 1</String>
          <String>$Syn 2</String>
          <String>$Syn 3</String>
        </FieldNames>
      </FieldTagData>
    </ScriptBased>
  </FieldTags>
</DocInternals>
